{"title":"About Me","uid":"baf07de6a0e53ebe319cefecf3aae4f5","text":"pub struct Rumple &#123; pub name: String, pub location: String, pub age: u8, pub hobby: Vec&lt;String&gt;, pub constellation: String, pub m...","date":"2020-10-14T02:59:15.000Z","updated":"2021-12-11T02:10:04.781Z","comments":true,"path":"api/pages/about/index.json","covers":null,"excerpt":"","content":"<pre class=\"line-numbers language-rust\" data-language=\"rust\"><code class=\"language-rust\">pub struct Rumple &#123;\n    pub name: String,\n    pub location: String,\n    pub age: u8,\n    pub hobby: Vec&lt;String&gt;,\n    pub constellation: String,\n    pub mail: String,\n    pub motto: String,\n&#125;\n\nimpl Rumple &#123;\n    fn new() -&gt; Rumple &#123;\n        Rumple &#123;\n            name: &quot;rumple&quot;.to_string(),\n            location: &quot;Shanghai&quot;.to_string(),\n            age: 28,\n            hobby: vec![\n                &quot;Basketball&quot;.to_string(),\n                &quot;Swim&quot;.to_string(),\n                &quot;Read&quot;.to_string(),\n                &quot;Code&quot;.to_string(),\n                &quot;Games&quot;.to_string(),\n            ],\n            constellation: &quot;Gemini&quot;.to_string(),\n            mail: &quot;d3JwMzU3NzExNTg5QDE2My5jb20&quot;.to_string(),\n            motto: &quot;All magic comes with a price&quot;.to_string(),\n        &#125;\n    &#125;\n\n    fn eat(&amp;self) &#123;\n        println!(&quot;&#123;&#125; eating&quot;, self.name);\n    &#125;\n\n    fn code(&amp;self) &#123;\n        println!(&quot;&#123;&#125; coding&quot;, self.name);\n    &#125;\n\n    fn sleep(&amp;self) &#123;\n        println!(&quot;&#123;&#125; sleeping&quot;, self.name);\n    &#125;\n\n    fn life(&amp;self) &#123;\n        loop &#123;\n            self.eat();\n            self.code();\n            self.sleep();\n        &#125;\n    &#125;\n&#125;\n\n\nfn main() &#123;\n    Rumple::new().life()\n&#125;</code></pre>\n\n<pre class=\"line-numbers language-go\" data-language=\"go\"><code class=\"language-go\">package main\n\nimport &quot;fmt&quot;\n\ntype Rumple struct &#123;\n\tName          string   &#96;json:&quot;name,omitempty&quot;&#96;\n\tAge           uint8    &#96;json:&quot;age,omitempty&quot;&#96;\n\tLocation      string   &#96;json:&quot;location,omitempty&quot;&#96;\n\tHobby         []string &#96;json:&quot;hobby,omitempty&quot;&#96;\n\tConstellation string   &#96;json:&quot;constellation,omitempty&quot;&#96;\n\tMail          string   &#96;json:&quot;mail,omitempty&quot;&#96;\n\tMotto         string   &#96;json:&quot;motto,omitempty&quot;&#96;\n&#125;\n\nfunc NewRumple() *Rumple &#123;\n\treturn &amp;Rumple&#123;\n\t\tName:          &quot;Rumple&quot;,\n\t\tAge:           28,\n\t\tLocation:      &quot;Shanghai&quot;,\n\t\tHobby:         []string&#123;&quot;Basketball&quot;, &quot;Swim&quot;, &quot;Read&quot;, &quot;Code&quot;, &quot;Games&quot;&#125;,\n\t\tConstellation: &quot;Gemini&quot;,\n\t\tMail:          &quot;d3JwMzU3NzExNTg5QDE2My5jb20&#x3D;&quot;,\n\t\tMotto:         &quot;All magic comes with a price&quot;,\n\t&#125;\n&#125;\n\nfunc (r *Rumple) Eat() &#123;\n\tfmt.Println(r.Name, &quot; eating&quot;)\n&#125;\n\nfunc (r *Rumple) Sleep() &#123;\n\tfmt.Println(r.Name, &quot; sleeping&quot;)\n&#125;\n\nfunc (r *Rumple) Code() &#123;\n\tfmt.Println(r.Name, &quot; coding&quot;)\n&#125;\n\nfunc (r *Rumple) Life() &#123;\n\talive :&#x3D; true\n\n\tfor alive &#123;\n\t\tr.Eat()\n\t\tr.Code()\n\t\tr.Sleep()\n\t&#125;\n\n&#125;\n\nfunc main() &#123;\n\tNewRumple().Life()\n&#125;</code></pre>\n\n\n<pre class=\"line-numbers language-python\" data-language=\"python\"><code class=\"language-python\">class Rumple(object):\n  def __init__(self, name: str):\n    self.name &#x3D; name\n    self.location &#x3D; &quot;ShangHai&quot;\n    self.age &#x3D; 28\n    self.hobby &#x3D; [&quot;Basketball&quot;,&quot;Swim&quot;,&quot;Read&quot;,&quot;Code&quot;,&quot;Games&quot;]\n    self.constellation &#x3D; &quot;Gemini&quot;\n    self.mail &#x3D; &quot;d3JwMzU3NzExNTg5QDE2My5jb20&#x3D;&quot;\n    self.motto &#x3D; &quot;All magic comes with a price&quot;\n  \n  def eat(self):\n    pass\n\n  def code(self):\n    pass\n\n  def sleep(self):\n    pass\n\n  def life(self):\n    alive &#x3D; True\n    while alive:\n      self.eat()\n      self.code()\n      self.sleep()\n  \n\nif __name__ &#x3D;&#x3D; &#39;__main__&#39;:\n  rumple &#x3D; Rumple(&quot;rumple&quot;)\n  rumple.life()</code></pre>","count_time":{"symbolsCount":"3.6k","symbolsTime":"3 mins."},"toc":""}